.codacy.yml
.codebeatignore
.coveragerc
.gitattributes
.gitignore
.gitmodules
.pre-commit-config.yaml
.snyk
AUTHORS.md
CHANGES.md
LICENSE
MANIFEST.in
README.md
README.pypi
docs-requirements.txt
pytest.ini
requirements.txt
setup.cfg
setup.py
start_qrl.py
test-requirements.txt
versioneer.py
.circleci/config.yml
.github/ISSUE_TEMPLATE/bug_report.md
.github/ISSUE_TEMPLATE/feature_request.md
docs/Makefile
docs/authors.rst
docs/changes.rst
docs/conf.py
docs/index.rst
docs/license.rst
docs/_static/.gitignore
docs/misc/address.md
docs/proto/index.html
docs/proto/proto.md
examples/.gitkeep
src/__init__.py
src/qrl/__init__.py
src/qrl/_version.py
src/qrl/cli.py
src/qrl/grpcProxy.py
src/qrl/main.py
src/qrl/measure.py
src/qrl.egg-info/PKG-INFO
src/qrl.egg-info/SOURCES.txt
src/qrl.egg-info/dependency_links.txt
src/qrl.egg-info/entry_points.txt
src/qrl.egg-info/not-zip-safe
src/qrl.egg-info/requires.txt
src/qrl.egg-info/top_level.txt
src/qrl/core/AddressState.py
src/qrl/core/Block.py
src/qrl/core/BlockHeader.py
src/qrl/core/BlockMetadata.py
src/qrl/core/ChainManager.py
src/qrl/core/DifficultyTracker.py
src/qrl/core/ESyncState.py
src/qrl/core/GenesisBlock.py
src/qrl/core/Indexer.py
src/qrl/core/LastTransactions.py
src/qrl/core/Message.py
src/qrl/core/MessageRequest.py
src/qrl/core/Miner.py
src/qrl/core/MultiSigAddressState.py
src/qrl/core/OptimizedAddressState.py
src/qrl/core/OutgoingMessage.py
src/qrl/core/PaginatedBitfield.py
src/qrl/core/PaginatedData.py
src/qrl/core/PoWValidator.py
src/qrl/core/ProposalRecord.py
src/qrl/core/Singleton.py
src/qrl/core/State.py
src/qrl/core/StateContainer.py
src/qrl/core/StateMigration.py
src/qrl/core/TokenList.py
src/qrl/core/TokenMetadata.py
src/qrl/core/TransactionInfo.py
src/qrl/core/TransactionMetadata.py
src/qrl/core/TransactionPool.py
src/qrl/core/VoteStats.py
src/qrl/core/Wallet.py
src/qrl/core/__init__.py
src/qrl/core/config.py
src/qrl/core/formulas.py
src/qrl/core/genesis.yml
src/qrl/core/messagereceipt.py
src/qrl/core/node.py
src/qrl/core/qrlnode.py
src/qrl/core/miners/__init__.py
src/qrl/core/miners/qrandomx/QRXMiner.py
src/qrl/core/miners/qrandomx/QRXPoWValidator.py
src/qrl/core/miners/qrandomx/__init__.py
