Metadata-Version: 1.1
Name: qrl
Version: 3.0.1
Summary: Quantum Resistant Ledger Node
Home-page: https://theqrl.org
Author: The Quantum Resistant Ledger Team
Author-email: info@theQRL.org
License: MIT
Platform: any
Classifier: Development Status :: 4 - Beta
Classifier: Programming Language :: Python
Classifier: Programming Language :: Python :: 3
Classifier: Programming Language :: Python :: 3.5
